asymcat/__init__.py
asymcat/common.py
asymcat/correlation.py
asymcat/py.typed
asymcat/scorer.py
asymcat-0.4.0.dist-info/licenses/LICENSE
asymcat-0.4.0.dist-info/METADATA
asymcat-0.4.0.dist-info/WHEEL
asymcat-0.4.0.dist-info/top_level.txt
asymcat-0.4.0.dist-info/RECORD
