Metadata-Version: 2.4
Name: asymcat
Version: 0.4.0
Summary: A Python library for obtaining asymmetric measures of association between categorical variables in data exploration and description
Author-email: Tiago Tresoldi <tiago.tresoldi@lingfil.uu.se>
Maintainer-email: Tiago Tresoldi <tiago.tresoldi@lingfil.uu.se>
License-Expression: MIT
Project-URL: Homepage, https://github.com/tresoldi/asymcat
Project-URL: Documentation, https://github.com/tresoldi/asymcat/blob/master/docs/USER_GUIDE.md
Project-URL: Repository, https://github.com/tresoldi/asymcat.git
Project-URL: Issues, https://github.com/tresoldi/asymcat/issues
Project-URL: Changelog, https://github.com/tresoldi/asymcat/blob/master/CHANGELOG.md
Keywords: categorical,association,asymmetric,data-analysis,statistics
Classifier: Development Status :: 4 - Beta
Classifier: Intended Audience :: Developers
Classifier: Intended Audience :: Science/Research
Classifier: Operating System :: OS Independent
Classifier: Programming Language :: Python :: 3
Classifier: Programming Language :: Python :: 3.10
Classifier: Programming Language :: Python :: 3.11
Classifier: Programming Language :: Python :: 3.12
Classifier: Programming Language :: Python :: Implementation :: CPython
Classifier: Programming Language :: Python :: Implementation :: PyPy
Classifier: Topic :: Scientific/Engineering
Classifier: Topic :: Scientific/Engineering :: Information Analysis
Classifier: Topic :: Scientific/Engineering :: Mathematics
Classifier: Topic :: Software Development :: Libraries
Classifier: Typing :: Typed
Requires-Python: >=3.10
License-File: LICENSE
Requires-Dist: freqprob>=0.4.0
Requires-Dist: matplotlib
Requires-Dist: numpy
Requires-Dist: pandas
Requires-Dist: scipy
Requires-Dist: seaborn
Requires-Dist: tabulate
Provides-Extra: dev
Requires-Dist: pytest>=7.0.0; extra == "dev"
Requires-Dist: pytest-cov>=4.0.0; extra == "dev"
Requires-Dist: pytest-xdist>=3.0.0; extra == "dev"
Requires-Dist: hypothesis>=6.0.0; extra == "dev"
Requires-Dist: ruff>=0.1.0; extra == "dev"
Requires-Dist: mypy>=1.5.0; extra == "dev"
Requires-Dist: build>=0.10.0; extra == "dev"
Requires-Dist: twine>=4.0.0; extra == "dev"
Requires-Dist: nhandu>=0.1.0; extra == "dev"
Provides-Extra: all
Requires-Dist: asymcat[dev]; extra == "all"
Dynamic: license-file
